presalytics_doc_converter/__init__.py
presalytics_doc_converter/api_client.py
presalytics_doc_converter/configuration.py
presalytics_doc_converter/exceptions.py
presalytics_doc_converter/rest.py
presalytics_doc_converter/api/__init__.py
presalytics_doc_converter/api/default_api.py
presalytics_doc_converter/models/__init__.py
presalytics_doc_converter/models/file_to_convert.py
presalytics_doc_converter-0.2.21.dist-info/LICENSE
presalytics_doc_converter-0.2.21.dist-info/METADATA
presalytics_doc_converter-0.2.21.dist-info/WHEEL
presalytics_doc_converter-0.2.21.dist-info/top_level.txt
presalytics_doc_converter-0.2.21.dist-info/RECORD
