Metadata-Version: 2.1
Name: presalytics-doc-converter
Version: 0.2.21
Summary: Doc Converter API
Home-page: http://github.com/presalytics/doc-converter-python-client
Author-email: kevin@presalytics.io
License: UNKNOWN
Keywords: OpenAPI,OpenAPI-Generator,Doc Converter API
Platform: UNKNOWN
Requires-Dist: urllib3 (>=1.15)
Requires-Dist: six (>=1.10)
Requires-Dist: certifi
Requires-Dist: python-dateutil
